{
	"forge_marker": 1,
  	"defaults": {
    	"textures": {
      	"frozenpride": "kk:items/models/frozenpride"
      },
      "model": "kk:frozenpride.obj"
  	},
	"variants": {
  	"inventory": [
    	{
      	"transform": {
					"thirdperson_lefthand": {
						"rotation": [ { "x": -90 }, { "y": 90 }, { "z": 0 } ],
						"translation": [ 0.1, -0.1, 0.2 ],
						"scale": 0.012
					},
					"thirdperson_righthand": {
						"rotation": [ { "x": -90 }, { "y": 90 }, { "z": 0 } ],
						"translation": [ 0.1, -0.1, 0.2 ],
						"scale": 0.012
					},
					"gui": {
						"rotation": [ { "x": 0 }, { "y": 0 }, { "z": 0 } ],
						"translation": [ 0, 0, 0 ],
						"scale": 0.007
					},
					"firstperson_righthand": {
						"rotation": [ { "x": 180 }, { "y": 0 }, { "z": 170 } ],
						"translation": [ 0, -0.1, 0 ],
						"scale": 0.009
					},
					"firstperson_lefthand": {
						"rotation": [ { "x": 180 }, { "y": 0 }, { "z": 170 } ],
						"translation": [ 0, -0.1, 0 ],
						"scale": 0.009
					},
					"ground": {
						"rotation": [ { "x": 45 }, { "y": 0 }, { "z": 0 } ],
						"scale": 0.01
					}
        }
      }
    ],
		"overrides": [
      {
        "predicate": {
          "blocking": 1
        },
        "model": "kk:kingdomkey.obj"
      }
    ]
  }
}
