{
	"forge_marker": 1,
    "defaults": {
    	"textures": {

    		},
        "model": "kk:lindworm.obj"
    },
	"variants": {
        "inventory": [
            {
                "transform": {
                    "thirdperson_lefthand": {
                        "rotation": [ { "x": 0 }, { "y": 180 }, { "z": 0 } ],
                        "translation": [ 0, 0, 0.05 ],
                        "scale": 0.025
                    },
                    "thirdperson_righthand": {
                        "rotation": [ { "x": 0 }, { "y": 180 }, { "z": 0 } ],
                        "translation": [ -0.05, 0, 0.05 ],
                        "scale": 0.025
                    },
                    "gui": {
                        "rotation": [ { "x": 0 }, { "y": 0 }, { "z": 30 } ],
                        "translation": [ 0, 0, 0 ],
                        "scale": 0.008
                    },
                    "firstperson_righthand": {
                        "rotation": [ { "x": 0 }, { "y": 180 }, { "z": 0 } ],
                        "translation": [ 0, 0.3, 0 ],
                        "scale": 0.01
                    },
                    "firstperson_lefthand": {
                        "rotation": [ { "x": 0 }, { "y": 180 }, { "z": 0 } ],
                        "translation": [ 0, 0.3, 0 ],
                        "scale": 0.01
                    },
                    "ground": {
                        "rotation": [ { "x": 45 }, { "y": 0 }, { "z": 0 } ],
                        "scale": 0.008
                    }
                }
            }
        ]
    }
}
